{
  "project_info": {
    "project_number": "458193872335",
    "project_id": "astqrar65",
    "storage_bucket": "astqrar65.appspot.com"
  },
  "client": [
    {
      "client_info": {
        "mobilesdk_app_id": "1:458193872335:android:14499751ed36c9823bdeba",
        "android_client_info": {
          "package_name": "com.astqrar.com"
        }
      },
      "oauth_client": [
        {
          "client_id": "458193872335-utesjdoa315472ro2lmo0t1d40ub4480.apps.googleusercontent.com",
          "client_type": 3
        }
      ],
      "api_key": [
        {
          "current_key": "AIzaSyB7usHblSxEooxPFyFQN40S42LSJzVGBNE"
        }
      ],
      "services": {
        "appinvite_service": {
          "other_platform_oauth_client": [
            {
              "client_id": "458193872335-utesjdoa315472ro2lmo0t1d40ub4480.apps.googleusercontent.com",
              "client_type": 3
            }
          ]
        }
      }
    }
  ],
  "configuration_version": "1"
}